gfix/__init__.py
gfix/main.py
gfix-0.0.0.dist-info/METADATA
gfix-0.0.0.dist-info/WHEEL
gfix-0.0.0.dist-info/entry_points.txt
gfix-0.0.0.dist-info/top_level.txt
gfix-0.0.0.dist-info/RECORD
