Metadata-Version: 2.1
Name: gfix
Version: 0.0.0
Home-page: https://github.com/sbooeshaghi/gfix
Author: Sina Booeshaghi
Author-email: sinab@berkeley.edu
Maintainer: Sina Booeshaghi
Maintainer-email: sinab@berkeley.edu
License: MIT
Classifier: Environment :: Console
Classifier: Intended Audience :: Science/Research
Classifier: License :: OSI Approved :: MIT License
Classifier: Operating System :: OS Independent
Classifier: Programming Language :: Python :: 3.6
Classifier: Programming Language :: Python :: 3.7
Classifier: Programming Language :: Python :: 3.8
Classifier: Programming Language :: Python :: 3.9
Classifier: Programming Language :: Python :: 3.10
Classifier: Topic :: Scientific/Engineering :: Bio-Informatics
Classifier: Topic :: Utilities
Requires-Python: >=3.6
Requires-Dist: pandas
Requires-Dist: numpy
